ai_university/__init__.py
ai_university/demo.py
ai_university_ALKER-1.0.2.dist-info/LICENSE.txt
ai_university_ALKER-1.0.2.dist-info/METADATA
ai_university_ALKER-1.0.2.dist-info/WHEEL
ai_university_ALKER-1.0.2.dist-info/top_level.txt
ai_university_ALKER-1.0.2.dist-info/RECORD
